quickcerts/__init__.py
quickcerts/__main__.py
quickcerts-1.2.0.dist-info/LICENSE
quickcerts-1.2.0.dist-info/METADATA
quickcerts-1.2.0.dist-info/WHEEL
quickcerts-1.2.0.dist-info/entry_points.txt
quickcerts-1.2.0.dist-info/top_level.txt
quickcerts-1.2.0.dist-info/zip-safe
quickcerts-1.2.0.dist-info/RECORD
