Metadata-Version: 2.1
Name: quickcerts
Version: 1.2.0
Summary: Quick and easy X.509 certificate generator for SSL/TLS utilizing local PKI
Home-page: https://github.com/Snawoot/quickcerts
Author: Vladislav Yarmak
Author-email: vladislav-ex-src@vm-0.com
License: MIT
Classifier: Programming Language :: Python :: 3.4
Classifier: License :: OSI Approved :: MIT License
Classifier: Operating System :: OS Independent
Classifier: Development Status :: 5 - Production/Stable
Classifier: Environment :: Console
Classifier: Intended Audience :: Developers
Classifier: Intended Audience :: End Users/Desktop
Classifier: Intended Audience :: Telecommunications Industry
Classifier: Intended Audience :: System Administrators
Classifier: Intended Audience :: Other Audience
Classifier: Natural Language :: English
Classifier: Topic :: Communications :: Email :: Mail Transport Agents
Classifier: Topic :: Internet
Classifier: Topic :: Security
Classifier: Topic :: Internet :: Proxy Servers
Classifier: Topic :: Security :: Cryptography
Classifier: Topic :: Utilities
Requires-Python: >=3.4
License-File: LICENSE
Requires-Dist: cryptography (>=1.6)
